tot_multi/__init__.py
tot_multi/multi.py
tot_multi-0.1.2.dist-info/METADATA
tot_multi-0.1.2.dist-info/WHEEL
tot_multi-0.1.2.dist-info/entry_points.txt
tot_multi-0.1.2.dist-info/top_level.txt
tot_multi-0.1.2.dist-info/RECORD
