Metadata-Version: 2.1
Name: tot_multi
Version: 0.1.2
Summary: Default template for PDM package
Author-email: EstherCho-7 <dkgkqm777@gmail.com>
License: MIT
Requires-Python: >=3.9
